counter.v
module counter #(
    parameter N = 8
) (
    input clk, reset, enable,
    output [3:0] out, 
    output done
);

reg [3:0] out_r;
reg done_r;

always @(posedge clk, posedge reset)
begin
    done_r <= 0;
    if (reset == 1)
        out_r <= 0;
    else
    begin
        if (enable == 1)
        begin
            if (out_r + 1 == N)
            begin
                out_r <= 0;
                done_r <= 1;
            end
            else
                out_r <= out_r + 1;
        end
        else
            out_r <= out_r;
    end
end

assign out = out_r;
assign done = done_r;
    
endmodule

counter_tb.v
`timescale 1ns/1ps   // Always set timescale for consistency

module counter_tb;

    // =========================================================
    // Clock & Reset
    // =========================================================
    reg clk_tb;
    reg rst_tb;

    // Clock generation: toggle every 1 time unit -> 2ns period
    initial clk_tb = 0;
    always #1 clk_tb = ~clk_tb;

    // Reset generation
    initial begin
        rst_tb = 1;
        #5 rst_tb = 0;   // deassert reset after 5 time units
    end

    // =========================================================
    // DUT I/O Signals
    // =========================================================
    // Declare test bench-controlled regs for inputs
    reg  en_tb;
    // Declare wires to capture outputs
    wire [3:0] out_tb;
    wire done_tb;

    // =========================================================
    // DUT Instantiation
    // =========================================================
    // Replace `template` with the name of your DUT
    counter DUT (
        .clk    (clk_tb),
        .reset  (rst_tb),
        .enable (en_tb),
        .out    (out_tb),
        .done   (done_tb)
    );

    // =========================================================
    // Stimulus
    // =========================================================
    initial begin
        // Initialize inputs
        en_tb = 0;

        // Monitor outputs (prints when any monitored var changes)
        $monitor("Time=%0t | rst=%b | en=%b | out=%b | done=%b", 
                 $time, rst_tb, en_tb, out_tb, done_tb);

        // Wait until reset finishes
        @(negedge rst_tb);

        // Test case 1
        #10 
        en_tb = 1; #50 // Let enable be high for 50 time units (25 clock cycles)
        en_tb = 0;

        // Test case 2
        #10;

        // Test case 3
        #10;

        // Wrap up simulation
        #20 $finish;
    end

    // =========================================================
    // Waveform Dump (for GTKWave, ModelSim, etc.)
    // =========================================================
    initial begin
        $dumpfile("counter_tb.vcd");   // name of VCD dump file
        $dumpvars(0, counter_tb);      // dump all signals in tb
    end

endmodule

counter_tb.vcd
$date
	Sun Sep  7 20:17:48 2025
$end
$version
	Icarus Verilog
$end
$timescale
	1ps
$end
$scope module counter_tb $end
$var wire 4 ! out_tb [3:0] $end
$var wire 1 " done_tb $end
$var reg 1 # clk_tb $end
$var reg 1 $ en_tb $end
$var reg 1 % rst_tb $end
$scope module DUT $end
$var wire 1 # clk $end
$var wire 1 " done $end
$var wire 1 $ enable $end
$var wire 4 & out [3:0] $end
$var wire 1 % reset $end
$var parameter 32 ' N $end
$var reg 1 ( done_r $end
$var reg 4 ) out_r [3:0] $end
$upscope $end
$upscope $end
$enddefinitions $end
$comment Show the parameter values. $end
$dumpall
b1000 '
$end
#0
$dumpvars
b0 )
0(
b0 &
1%
0$
0#
0"
b0 !
$end
#1000
1#
#2000
0#
#3000
1#
#4000
0#
#5000
1#
0%
#6000
0#
#7000
1#
#8000
0#
#9000
1#
#10000
0#
#11000
1#
#12000
0#
#13000
1#
#14000
0#
#15000
b1 !
b1 &
b1 )
1#
1$
#16000
0#
#17000
b10 !
b10 &
b10 )
1#
#18000
0#
#19000
b11 !
b11 &
b11 )
1#
#20000
0#
#21000
b100 !
b100 &
b100 )
1#
#22000
0#
#23000
b101 !
b101 &
b101 )
1#
#24000
0#
#25000
b110 !
b110 &
b110 )
1#
#26000
0#
#27000
b111 !
b111 &
b111 )
1#
#28000
0#
#29000
1"
1(
b0 !
b0 &
b0 )
1#
#30000
0#
#31000
b1 !
b1 &
b1 )
0"
0(
1#
#32000
0#
#33000
b10 !
b10 &
b10 )
1#
#34000
0#
#35000
b11 !
b11 &
b11 )
1#
#36000
0#
#37000
b100 !
b100 &
b100 )
1#
#38000
0#
#39000
b101 !
b101 &
b101 )
1#
#40000
0#
#41000
b110 !
b110 &
b110 )
1#
#42000
0#
#43000
b111 !
b111 &
b111 )
1#
#44000
0#
#45000
1"
1(
b0 !
b0 &
b0 )
1#
#46000
0#
#47000
b1 !
b1 &
b1 )
0"
0(
1#
#48000
0#
#49000
b10 !
b10 &
b10 )
1#
#50000
0#
#51000
b11 !
b11 &
b11 )
1#
#52000
0#
#53000
b100 !
b100 &
b100 )
1#
#54000
0#
#55000
b101 !
b101 &
b101 )
1#
#56000
0#
#57000
b110 !
b110 &
b110 )
1#
#58000
0#
#59000
b111 !
b111 &
b111 )
1#
#60000
0#
#61000
1"
1(
b0 !
b0 &
b0 )
1#
#62000
0#
#63000
b1 !
b1 &
b1 )
0"
0(
1#
#64000
0#
#65000
1#
0$
